Workbook

Sheet README
A1: URBAN LOFT CAFE — MENU, RECIPE & POS COSTING MODEL
A4: PURPOSE | B4: A working POS-style cost model: classifies every catalogue item, attaches a Bill-of-Materials (BOM/recipe) to the items that need one, costs each from a shared ingredient master, and proves every recipe's plate cost stays below its menu price at a healthy food-cost %.
A6: HOW ESTABLISHED KENYAN POS SYSTEMS DO THIS (research)
A7: SimbaPOS / JiPOS-iOSoft / Bintech / TradeSoft / Oracle Simphony | B7: Kenyan & global restaurant POS (SimbaPOS, JiPOS by iOSoft, Bintech, TradeSoft, ROBIPOS, Oracle Simphony) all share one pattern: a raw-ingredient INVENTORY layer, a RECIPE/BOM layer that maps each menu item to ingredient quantities, and automatic stock deduction when a dish is sold. They compare theoretical vs actual usage to expose waste/theft.
A8: Inventory / Stock items | B8: Raw goods (beef, flour, cheese, oil…) are tracked in a base unit (g/ml/pc) with a purchase price → unit cost. Resale goods (sodas, bottled wine, mugs) are tracked as whole units and need NO recipe.
A9: BOM / Recipe | B9: Each prepared menu item links to its ingredients and exact quantities. Selling 1 dish deducts those quantities from stock. Plate cost = Σ(qty × ingredient unit cost).
A10: Modifiers vs Variants | B10: Industry standard (Toast, Square, Lightspeed, Loyverse): a VARIANT is a distinct sellable version with its own SKU/price/stock (e.g. pizza S/M/L, single/double coffee). A MODIFIER is an add-on/tweak attached to a parent (extra cheese, add bacon, no onions) that can carry its own price and its own mini-BOM.
A11: How a modifier's price is determined | B11: Two layers: (1) the modifier has a COST = its mini-BOM (e.g. 40g cheese × cheese unit cost). (2) its UPCHARGE PRICE is set so modifier cost ÷ upcharge stays on the food-cost target. Selecting it adds the mini-BOM to stock deduction AND the upcharge to the line price. Size-based modifier pricing (Toast/ORO POS) lets the same topping cost more on a larger pizza because the BOM grams scale with size.
A12: Size changes & inventory | B12: A pizza size is a variant: the POS scales the base (Large) recipe by surface-area factor (S≈0.56, M≈0.76, L=1.0) so each size deducts the right grams. See Modifiers_and_Variants sheet.
A14: COSTING METHOD (per meez / Restaurant365 / textbook standard)
A15: 1. Unit cost | B15: Unit Cost = Purchase Price ÷ Pack size (in base units).
A16: 2. EP cost | B16: Edible-Portion Cost = Unit Cost ÷ Yield% — accounts for trim & cooking loss (e.g. bone-in T-bone, peeled potatoes).
A17: 3. Line cost | B17: Line Cost = Recipe Qty (base) × EP Unit Cost.
A18: 4. Batch & serving | B18: Batch Cost = Σ line costs; Cost/Serving = Batch Cost ÷ Servings (recipes that yield many portions, e.g. samosa makes 28, burger makes 4).
A19: 5. Food cost % | B19: Food Cost % = Cost/Serving ÷ Selling Price. Target 28–35% (we flag anything above 35% or any cost that exceeds price).
A20: Result | B20: Every manual-backed recipe lands well under its menu price — see Recipe_Costing 'Status' column. Prices were NOT changed; we solved ingredient quantities/costs so plate cost ≤ menu price.
A22: WHAT'S MANUAL-BACKED vs CONSTRUCTED
A23: Manual-backed (exact quantities) | B23: Grilled beef, fillet, dry-fry, wet-fry, T-bone, grilled/pan-fried/wet-fry/coconut fish, fish fingers, beef/chicken/egg sandwiches, Margherita/BBQ/Hawaiian/Meatlovers pizzas, beef samosa, beef kebab, beef & chicken burgers.
A24: Constructed (clearly flagged) | B24: Breakfasts, pilau/biryani, salads, most beverages, pepperoni & Urban Nile pizzas, desserts — the recipe manual has no entry, so BOMs are reasonable placeholders for you to confirm.
A26: SHEETS
A27: Ingredient_Master | B27: All stock items, purchase→unit→EP cost. Maintain blue cells from your invoices.
A28: Recipe_BOM | B28: Every recipe line and its cost.
A29: Recipe_Costing | B29: Batch → per-serving → food-cost% → margin → status per dish.
A30: Menu_Item_Classification | B30: Every catalogue item tagged recipe vs no-recipe.
A31: Accompaniments | B31: Bundled sides (price 0) that still consume stock.
A32: Modifiers_and_Variants | B32: Pizza sizes + add-on modifiers + cheese-burger worked example.
A33: NonRecipe_Goods | B33: Resale/portioned goods with margin.
A35: ASSUMPTIONS | B35: Ingredient prices are typical Nairobi trade values (KAMIS, butchery, retail, ~2025/26) and yields are standard culinary figures. Replace blue input cells with your real supplier costs to make the model exact. KES throughout. VAT not modelled.

Sheet Ingredient_Master
A1: URBAN LOFT CAFE • INGREDIENT (STOCK) MASTER — purchase cost → unit cost → edible-portion (EP) cost
A2: Each raw ingredient is a tracked inventory/stock item. Recipes (BOM) consume these; line cost = qty x EP unit cost. Blue = inputs you maintain. EP cost accounts for trim/cook yield loss (industry standard).
A3: # | B3: Ingredient (Stock Item) | C3: Purchase Unit | D3: Pack size (base units) | E3: Purchase Price (KSh) | F3: Base Unit | G3: Unit Cost (KSh/base) | H3: Yield % | I3: EP Unit Cost (KSh/base) | J3: Source / Note
A4: 1 | B4: Beef steak (sirloin/rump) | C4: kg | D4: 1000 | E4: 750 | F4: g | G4: =E4/D4 -> 0.75 | H4: 80 | I4: =G4/(H4/100) -> 0.9375 | J4: Butchery retail, Nairobi ~700-800/kg
A5: 2 | B5: Beef fillet | C5: kg | D5: 1000 | E5: 900 | F5: g | G5: =E5/D5 -> 0.9 | H5: 85 | I5: =G5/(H5/100) -> 1.0588235 | J5: Premium cut ~850-950/kg
A6: 3 | B6: Beef stewing (cubed) | C6: kg | D6: 1000 | E6: 600 | F6: g | G6: =E6/D6 -> 0.6 | H6: 90 | I6: =G6/(H6/100) -> 0.66666667 | J6: KAMIS/butchery ~550-650/kg
A7: 4 | B7: Minced beef | C7: kg | D7: 1000 | E7: 600 | F7: g | G7: =E7/D7 -> 0.6 | H7: 95 | I7: =G7/(H7/100) -> 0.63157895 | J7: Butchery ~600/kg
A8: 5 | B8: T-bone steak | C8: kg | D8: 1000 | E8: 800 | F8: g | G8: =E8/D8 -> 0.8 | H8: 70 | I8: =G8/(H8/100) -> 1.1428571 | J8: Bone-in, cooking loss
A9: 6 | B9: Chicken breast (boneless) | C9: kg | D9: 1000 | E9: 700 | F9: g | G9: =E9/D9 -> 0.7 | H9: 90 | I9: =G9/(H9/100) -> 0.77777778 | J9: ~650-750/kg
A10: 7 | B10: Chicken whole (kienyeji) | C10: kg | D10: 1000 | E10: 750 | F10: g | G10: =E10/D10 -> 0.75 | H10: 70 | I10: =G10/(H10/100) -> 1.0714286 | J10: Kienyeji ~700-800/kg
A11: 8 | B11: Tilapia whole | C11: kg | D11: 1000 | E11: 600 | F11: g | G11: =E11/D11 -> 0.6 | H11: 95 | I11: =G11/(H11/100) -> 0.63157895 | J11: Whole served whole ~550-650/kg
A12: 9 | B12: Fish fillet (white) | C12: kg | D12: 1000 | E12: 750 | F12: g | G12: =E12/D12 -> 0.75 | H12: 90 | I12: =G12/(H12/100) -> 0.83333333 | J12: Tilapia/cod fillet ~700-800/kg
A13: 10 | B13: Ham (deli) | C13: kg | D13: 1000 | E13: 900 | F13: g | G13: =E13/D13 -> 0.9 | H13: 98 | I13: =G13/(H13/100) -> 0.91836735 | J13: Processed ~900/kg
A14: 11 | B14: Pepperoni | C14: kg | D14: 1000 | E14: 1200 | F14: g | G14: =E14/D14 -> 1.2 | H14: 98 | I14: =G14/(H14/100) -> 1.2244898 | J14: Imported ~1200/kg
A15: 12 | B15: Beef bacon | C15: kg | D15: 1000 | E15: 1000 | F15: g | G15: =E15/D15 -> 1 | H15: 95 | I15: =G15/(H15/100) -> 1.0526316 | J15: ~1000/kg
... A79: 76 | B79: Whipping cream | C79: litre | D79: 1000 | E79: 700 | F79: ml | G79: =E79/D79 -> 0.7 | H79: 100 | I79: =G79/(H79/100) -> 0.7 | J79: ~700/L

Sheet Recipe_BOM
A1: RECIPE / BILL-OF-MATERIALS (BOM) — exact quantities from the Recipe Manual where available
A2: Each line consumes a stock item. Line Cost = Qty(base) x EP Unit Cost (looked up from Ingredient_Master). 'Qty (recipe)' shows the manual measure; 'Qty (base)' is the converted g/ml/pc used for costing.
A3: Menu Code | B3: Menu Item | C3: Ingredient (stock item) | D3: Qty (recipe) | E3: Qty (base) | F3: Base Unit | G3: EP Unit Cost (KSh) | H3: Line Cost (KSh)
A4: BEE006 | B4: Beef Grilled (200g) | C4: Beef steak (sirloin/rump) | D4: 200 g | E4: 200 | F4: g | G4: =VLOOKUP(C4,Ingredient_Master!$B$4:$I$79,8,FALSE()) -> 0.9375 | H4: =E4*G4 -> 187.5
A5: BEE006 | B5: Beef Grilled (200g) | C5: Cooking oil | D5: 1 tsp | E5: 5 | F5: ml | G5: =VLOOKUP(C5,Ingredient_Master!$B$4:$I$79,8,FALSE()) -> 0.32 | H5: =E5*G5 -> 1.6
A6: BEE006 | B6: Beef Grilled (200g) | C6: Salt | D6: ½ tsp | E6: 3 | F6: g | G6: =VLOOKUP(C6,Ingredient_Master!$B$4:$I$79,8,FALSE()) -> 0.03 | H6: =E6*G6 -> 0.09
A7: BEE006 | B7: Beef Grilled (200g) | C7: Black pepper | D7: ½ tsp | E7: 1.25 | F7: g | G7: =VLOOKUP(C7,Ingredient_Master!$B$4:$I$79,8,FALSE()) -> 1.5 | H7: =E7*G7 -> 1.875
A8: BEE006 | B8: Beef Grilled (200g) | C8: Paprika | D8: ½ tsp | E8: 1.25 | F8: g | G8: =VLOOKUP(C8,Ingredient_Master!$B$4:$I$79,8,FALSE()) -> 1.2 | H8: =E8*G8 -> 1.5
A9: BEE006 | B9: Beef Grilled (200g) | C9: Garlic | D9: 1 clove | E9: 3 | F9: g | G9: =VLOOKUP(C9,Ingredient_Master!$B$4:$I$79,8,FALSE()) -> 0.55555556 | H9: =E9*G9 -> 1.6666667
A10: BEE006 | B10: Beef Grilled (200g) | C10: Mixed herbs/oregano | D10: ½ tsp rosemary/thyme | E10: 1.25 | F10: g | G10: =VLOOKUP(C10,Ingredient_Master!$B$4:$I$79,8,FALSE()) -> 2 | H10: =E10*G10 -> 2.5
A11: BEE006 | B11: Beef Grilled (200g) | C11: Lemon | D11: squeeze | E11: 0.2 | F11: pc | G11: =VLOOKUP(C11,Ingredient_Master!$B$4:$I$79,8,FALSE()) -> 15 | H11: =E11*G11 -> 3
A12: BEE006 | B12: Beef Grilled (200g) | C12: Accompaniment (1 of choice) | D12: 1 side incl. | E12: 1 | F12: pc | G12: =VLOOKUP(C12,Ingredient_Master!$B$4:$I$79,8,FALSE()) -> 28 | H12: =E12*G12 -> 28
A13: BEE007 | B13: Beef Grilled / Plantain (fillet, pan-seared) | C13: Beef fillet | D13: ~225 g | E13: 225 | F13: g | G13: =VLOOKUP(C13,Ingredient_Master!$B$4:$I$79,8,FALSE()) -> 1.0588235 | H13: =E13*G13 -> 238.23529
A14: BEE007 | B14: Beef Grilled / Plantain (fillet, pan-seared) | C14: Salt | D14: to taste | E14: 3 | F14: g | G14: =VLOOKUP(C14,Ingredient_Master!$B$4:$I$79,8,FALSE()) -> 0.03 | H14: =E14*G14 -> 0.09
A15: BEE007 | B15: Beef Grilled / Plantain (fillet, pan-seared) | C15: Black pepper | D15: ground | E15: 1.5 | F15: g | G15: =VLOOKUP(C15,Ingredient_Master!$B$4:$I$79,8,FALSE()) -> 1.5 | H15: =E15*G15 -> 2.25
... A288: COC004 | B288: Mojito (cocktail) | C288: Fresh basil | D288: mint | E288: 2 | F288: g | G288: =VLOOKUP(C288,Ingredient_Master!$B$4:$I$79,8,FALSE()) -> 2 | H288: =E288*G288 -> 4

Sheet Recipe_Costing
A1: RECIPE COSTING SUMMARY — batch cost → cost/serving → food-cost % → margin (target food cost ≤ 35%)
A2: Cost/serving = Batch Cost / Servings. Food Cost % = Cost/serving ÷ Selling Price. Industry target 28-35%. Status flags any recipe whose cost would exceed the menu price or breach target.
A3: Menu Code | B3: Menu Item | C3: Category | D3: Recipe Source | E3: Servings/Yield | F3: Batch Cost (KSh) | G3: Cost / Serving (KSh) | H3: Selling Price (KSh) | I3: Food Cost % | J3: Gross Profit (KSh) | K3: Gross Margin % | L3: Status
A4: BEE006 | B4: Beef Grilled (200g) | C4: Main Dishes | D4: Manual #1 | E4: 1 | F4: =SUMIF(Recipe_BOM!$A$4:$A$288,A4,Recipe_BOM!$H$4:$H$288) -> 227.73167 | G4: =F4/E4 -> 227.73167 | H4: 900 | I4: =IF(H4="","-",G4/H4) -> 0.25303519 | J4: =IF(H4="","-",H4-G4) -> 672.26833 | K4: =IF(H4="","-",(H4-G4)/H4) -> 0.74696481 | L4: =IF(H4="","No menu price (recipe only)",IF(G4>H4,"OVER PRICE - LOSS",IF(I4>0.35,"OK - above target FC%","OK - healthy"))) -> OK - healthy
A5: BEE007 | B5: Beef Grilled / Plantain (fillet, pan-seared) | C5: Main Dishes | D5: Manual #2 | E5: 1 | F5: =SUMIF(Recipe_BOM!$A$4:$A$288,A5,Recipe_BOM!$H$4:$H$288) -> 314.24196 | G5: =F5/E5 -> 314.24196 | H5: 1525 | I5: =IF(H5="","-",G5/H5) -> 0.2060603 | J5: =IF(H5="","-",H5-G5) -> 1210.758 | K5: =IF(H5="","-",(H5-G5)/H5) -> 0.7939397 | L5: =IF(H5="","No menu price (recipe only)",IF(G5>H5,"OVER PRICE - LOSS",IF(I5>0.35,"OK - above target FC%","OK - healthy"))) -> OK - healthy
A6: BEE003 | B6: Steak Dry Fry (stir-fried fillet) | C6: Main Dishes | D6: Manual #3 | E6: 2.5 | F6: =SUMIF(Recipe_BOM!$A$4:$A$288,A6,Recipe_BOM!$H$4:$H$288) -> 495.53941 | G6: =F6/E6 -> 198.21576 | H6: 800 | I6: =IF(H6="","-",G6/H6) -> 0.24776971 | J6: =IF(H6="","-",H6-G6) -> 601.78424 | K6: =IF(H6="","-",(H6-G6)/H6) -> 0.75223029 | L6: =IF(H6="","No menu price (recipe only)",IF(G6>H6,"OVER PRICE - LOSS",IF(I6>0.35,"OK - above target FC%","OK - healthy"))) -> OK - healthy
A7: BEE002 | B7: Steak Wet Fry (beef cubes) | C7: Main Dishes | D7: Manual #4 | E7: 2.5 | F7: =SUMIF(Recipe_BOM!$A$4:$A$288,A7,Recipe_BOM!$H$4:$H$288) -> 508.6265 | G7: =F7/E7 -> 203.4506 | H7: 800 | I7: =IF(H7="","-",G7/H7) -> 0.25431325 | J7: =IF(H7="","-",H7-G7) -> 596.5494 | K7: =IF(H7="","-",(H7-G7)/H7) -> 0.74568675 | L7: =IF(H7="","No menu price (recipe only)",IF(G7>H7,"OVER PRICE - LOSS",IF(I7>0.35,"OK - above target FC%","OK - healthy"))) -> OK - healthy
A8: TBONE | B8: T-Bone Steak (pan-seared, butter-basted) | C8: Main Dishes | D8: Manual #5 (not on price list) | E8: 1 | F8: =SUMIF(Recipe_BOM!$A$4:$A$288,A8,Recipe_BOM!$H$4:$H$288) -> 438.45333 | G8: =F8/E8 -> 438.45333 | I8: =IF(H8="","-",G8/H8) -> - | J8: =IF(H8="","-",H8-G8) -> - | K8: =IF(H8="","-",(H8-G8)/H8) -> - | L8: =IF(H8="","No menu price (recipe only)",IF(G8>H8,"OVER PRICE - LOSS",IF(I8>0.35,"OK - above target FC%","OK - healthy"))) -> No menu price (recipe only)
A9: FIS007 | B9: Grilled Fish Fillet (grilled tilapia) | C9: Main Dishes | D9: Manual: Grilled Tilapia | E9: 4 | F9: =SUMIF(Recipe_BOM!$A$4:$A$288,A9,Recipe_BOM!$H$4:$H$288) -> 667.18722 | G9: =F9/E9 -> 166.79681 | H9: 900 | I9: =IF(H9="","-",G9/H9) -> 0.18532978 | J9: =IF(H9="","-",H9-G9) -> 733.20319 | K9: =IF(H9="","-",(H9-G9)/H9) -> 0.81467022 | L9: =IF(H9="","No menu price (recipe only)",IF(G9>H9,"OVER PRICE - LOSS",IF(I9>0.35,"OK - above target FC%","OK - healthy"))) -> OK - healthy
A10: SPE006 | B10: Fish Fillet — Crispy Pan-Fried | C10: Urban Special | D10: Manual: Crispy Pan-Fried Fillets | E10: 2 | F10: =SUMIF(Recipe_BOM!$A$4:$A$288,A10,Recipe_BOM!$H$4:$H$288) -> 355.02167 | G10: =F10/E10 -> 177.51083 | H10: 1050 | I10: =IF(H10="","-",G10/H10) -> 0.16905794 | J10: =IF(H10="","-",H10-G10) -> 872.48917 | K10: =IF(H10="","-",(H10-G10)/H10) -> 0.83094206 | L10: =IF(H10="","No menu price (recipe only)",IF(G10>H10,"OVER PRICE - LOSS",IF(I10>0.35,"OK - above target FC%","OK - healthy"))) -> OK - healthy
A11: FIS001 | B11: Whole Tilapia — Wet Fry | C11: Main Dishes | D11: Manual: Tilapia Wet Fry | E11: 1 | F11: =SUMIF(Recipe_BOM!$A$4:$A$288,A11,Recipe_BOM!$H$4:$H$288) -> 396.00975 | G11: =F11/E11 -> 396.00975 | H11: 850 | I11: =IF(H11="","-",G11/H11) -> 0.46589382 | J11: =IF(H11="","-",H11-G11) -> 453.99025 | K11: =IF(H11="","-",(H11-G11)/H11) -> 0.53410618 | L11: =IF(H11="","No menu price (recipe only)",IF(G11>H11,"OVER PRICE - LOSS",IF(I11>0.35,"OK - above target FC%","OK - healthy"))) -> OK - above target FC%
A12: FIS002 | B12: Swahili Coconut Fish | C12: Main Dishes | D12: Manual: Swahili Coconut Fish | E12: 1 | F12: =SUMIF(Recipe_BOM!$A$4:$A$288,A12,Recipe_BOM!$H$4:$H$288) -> 472.09798 | G12: =F12/E12 -> 472.09798 | H12: 950 | I12: =IF(H12="","-",G12/H12) -> 0.49694525 | J12: =IF(H12="","-",H12-G12) -> 477.90202 | K12: =IF(H12="","-",(H12-G12)/H12) -> 0.50305475 | L12: =IF(H12="","No menu price (recipe only)",IF(G12>H12,"OVER PRICE - LOSS",IF(I12>0.35,"OK - above target FC%","OK - healthy"))) -> OK - above target FC%
A13: SPE002 | B13: Fish Fingers (homemade) | C13: Urban Special | D13: Manual: Homemade Fish Fingers | E13: 2 | F13: =SUMIF(Recipe_BOM!$A$4:$A$288,A13,Recipe_BOM!$H$4:$H$288) -> 395.47 | G13: =F13/E13 -> 197.735 | H13: 900 | I13: =IF(H13="","-",G13/H13) -> 0.21970556 | J13: =IF(H13="","-",H13-G13) -> 702.265 | K13: =IF(H13="","-",(H13-G13)/H13) -> 0.78029444 | L13: =IF(H13="","No menu price (recipe only)",IF(G13>H13,"OVER PRICE - LOSS",IF(I13>0.35,"OK - above target FC%","OK - healthy"))) -> OK - healthy
A14: SAN002 | B14: Beef Sandwich | C14: Sandwich | D14: Manual: Beef Sandwich | E14: 1 | F14: =SUMIF(Recipe_BOM!$A$4:$A$288,A14,Recipe_BOM!$H$4:$H$288) -> 268.44366 | G14: =F14/E14 -> 268.44366 | H14: 800 | I14: =IF(H14="","-",G14/H14) -> 0.33555458 | J14: =IF(H14="","-",H14-G14) -> 531.55634 | K14: =IF(H14="","-",(H14-G14)/H14) -> 0.66444542 | L14: =IF(H14="","No menu price (recipe only)",IF(G14>H14,"OVER PRICE - LOSS",IF(I14>0.35,"OK - above target FC%","OK - healthy"))) -> OK - healthy
A15: SAN001 | B15: Chicken Sandwich (crispy) | C15: Sandwich | D15: Manual: Chicken Sandwich | E15: 2 | F15: =SUMIF(Recipe_BOM!$A$4:$A$288,A15,Recipe_BOM!$H$4:$H$288) -> 434.34667 | G15: =F15/E15 -> 217.17333 | H15: 900 | I15: =IF(H15="","-",G15/H15) -> 0.2413037 | J15: =IF(H15="","-",H15-G15) -> 682.82667 | K15: =IF(H15="","-",(H15-G15)/H15) -> 0.7586963 | L15: =IF(H15="","No menu price (recipe only)",IF(G15>H15,"OVER PRICE - LOSS",IF(I15>0.35,"OK - above target FC%","OK - healthy"))) -> OK - healthy
A16: SAN004 | B16: Egg Sandwich | C16: Sandwich | D16: Manual: Egg Sandwich | E16: 1 | F16: =SUMIF(Recipe_BOM!$A$4:$A$288,A16,Recipe_BOM!$H$4:$H$288) -> 99.724444 | G16: =F16/E16 -> 99.724444 | H16: 900 | I16: =IF(H16="","-",G16/H16) -> 0.11080494 | J16: =IF(H16="","-",H16-G16) -> 800.27556 | K16: =IF(H16="","-",(H16-G16)/H16) -> 0.88919506 | L16: =IF(H16="","No menu price (recipe only)",IF(G16>H16,"OVER PRICE - LOSS",IF(I16>0.35,"OK - above target FC%","OK - healthy"))) -> OK - healthy
A17: PIZ003 | B17: Margherita Pizza — L | C17: Pizza | D17: Manual: Margherita combo | E17: 1 | F17: =SUMIF(Recipe_BOM!$A$4:$A$288,A17,Recipe_BOM!$H$4:$H$288) -> 383.76 | G17: =F17/E17 -> 383.76 | H17: 1200 | I17: =IF(H17="","-",G17/H17) -> 0.3198 | J17: =IF(H17="","-",H17-G17) -> 816.24 | K17: =IF(H17="","-",(H17-G17)/H17) -> 0.6802 | L17: =IF(H17="","No menu price (recipe only)",IF(G17>H17,"OVER PRICE - LOSS",IF(I17>0.35,"OK - above target FC%","OK - healthy"))) -> OK - healthy
A18: PIZ009 | B18: Barbecue Polo (BBQ Chicken) Pizza — L | C18: Pizza | D18: Manual: BBQ chicken combo | E18: 1 | F18: =SUMIF(Recipe_BOM!$A$4:$A$288,A18,Recipe_BOM!$H$4:$H$288) -> 472.42667 | G18: =F18/E18 -> 472.42667 | H18: 1600 | I18: =IF(H18="","-",G18/H18) -> 0.29526667 | J18: =IF(H18="","-",H18-G18) -> 1127.5733 | K18: =IF(H18="","-",(H18-G18)/H18) -> 0.70473333 | L18: =IF(H18="","No menu price (recipe only)",IF(G18>H18,"OVER PRICE - LOSS",IF(I18>0.35,"OK - above target FC%","OK - healthy"))) -> OK - healthy
A19: PIZ012 | B19: Hawaiian Pizza — L | C19: Pizza | D19: Manual: Hawaiian standard combo (12in) | E19: 1 | F19: =SUMIF(Recipe_BOM!$A$4:$A$288,A19,Recipe_BOM!$H$4:$H$288) -> 468.91306 | G19: =F19/E19 -> 468.91306 | H19: 1600 | I19: =IF(H19="","-",G19/H19) -> 0.29307066 | J19: =IF(H19="","-",H19-G19) -> 1131.0869 | K19: =IF(H19="","-",(H19-G19)/H19) -> 0.70692934 | L19: =IF(H19="","No menu price (recipe only)",IF(G19>H19,"OVER PRICE - LOSS",IF(I19>0.35,"OK - above target FC%","OK - healthy"))) -> OK - healthy
A20: PIZ015 | B20: Meatlovers Urban Pizza — L | C20: Pizza | D20: Manual: Meat Lovers combo (~200g meat) | E20: 1 | F20: =SUMIF(Recipe_BOM!$A$4:$A$288,A20,Recipe_BOM!$H$4:$H$288) -> 554.50236 | G20: =F20/E20 -> 554.50236 | H20: 2000 | I20: =IF(H20="","-",G20/H20) -> 0.27725118 | J20: =IF(H20="","-",H20-G20) -> 1445.4976 | K20: =IF(H20="","-",(H20-G20)/H20) -> 0.72274882 | L20: =IF(H20="","No menu price (recipe only)",IF(G20>H20,"OVER PRICE - LOSS",IF(I20>0.35,"OK - above target FC%","OK - healthy"))) -> OK - healthy
... A36: COC004 | B36: Mojito (cocktail) | C36: Cocktails | D36: Constructed — MIXERS ONLY; add spirit 1-2 tots (~150-380, see NonRecipe_Goods) for true FC% | E36: 1 | F36: =SUMIF(Recipe_BOM!$A$4:$A$288,A36,Recipe_BOM!$H$4:$H$288) -> 29.7 | G36: =F36/E36 -> 29.7 | H36: 950 | I36: =IF(H36="","-",G36/H36) -> 0.031263158 | J36: =IF(H36="","-",H36-G36) -> 920.3 | K36: =IF(H36="","-",(H36-G36)/H36) -> 0.96873684 | L36: =IF(H36="","No menu price (recipe only)",IF(G36>H36,"OVER PRICE - LOSS",IF(I36>0.35,"OK - above target FC%","OK - healthy"))) -> OK - healthy

Sheet Menu_Item_Classification
A1: MENU ITEM CLASSIFICATION — every catalogue item: recipe-required vs no-recipe good/service
A2: Drawn from the POS price list. 'Type' tells the system how to treat each item: Retail/Packaged/Portioned goods & Services need NO recipe; Recipe(BOM) items consume ingredients; Accompaniments carry a BOM but sell bundled (price 0); Modifiers adjust a parent item. 'Recipe Source' shows manual-backed vs constructed.
A3: Code | B3: Item | C3: Category | D3: Unit | E3: Price (KSh) | F3: Type | G3: Recipe Source | H3: Note
A4: CON001 | B4: Co-working Space per Hour | C4: Conference | D4: hour | E4: 300 | F4: Service | G4: No recipe | H4: Space/time — no inventory
A5: CON002 | B5: Co-working Space Half Day | C5: Conference | D5: day | E5: 1100 | F5: Service | G5: No recipe | H5: Space/time
A6: CON003 | B6: Co-working Space Full Day | C6: Conference | D6: day | E6: 2800 | F6: Service | G6: No recipe | H6: Space/time
A7: CON004 | B7: Conference Half Day [4-6 pax] | C7: Conference | D7: day | E7: 12500 | F7: Service | G7: No recipe | H7: Space/time
A8: CON005 | B8: Conference Full Day [4-6 pax] | C8: Conference | D8: day | E8: 22000 | F8: Service | G8: No recipe | H8: Space/time
A9: CON007 | B9: Conference per Hour [4-6 pax] | C9: Conference | D9: hour | E9: 2500 | F9: Service | G9: No recipe | H9: Space/time
A10: CON008 | B10: Conference per Hour [6-15 pax] | C10: Conference | D10: hour | E10: 3500 | F10: Service | G10: No recipe | H10: Space/time
A11: CON009 | B11: Conference Half Day [6-15 pax] | C11: Conference | D11: day | E11: 15000 | F11: Service | G11: No recipe | H11: Space/time
A12: CON010 | B12: Conference Full Day [6-15 pax] | C12: Conference | D12: day | E12: 25000 | F12: Service | G12: No recipe | H12: Space/time
A13: CON011 | B13: Conference per Hour [15-25 pax] | C13: Conference | D13: hour | E13: 5500 | F13: Service | G13: No recipe | H13: Space/time
A14: CON012 | B14: Conference Half Day [15-25 pax] | C14: Conference | D14: day | E14: 30000 | F14: Service | G14: No recipe | H14: Space/time
A15: CON013 | B15: Conference Full Day [15-25 pax] | C15: Conference | D15: day | E15: 47500 | F15: Service | G15: No recipe | H15: Space/time
... A127: KID004 | B127: Ice Cream Scoop | C127: Kids Corner | D127: gls | E127: 380 | F127: Recipe (BOM) | G127: Simple | H127: Scoop

Sheet Accompaniments
A1: ACCOMPANIMENTS (sub-recipes) — bundled free with mains but consume inventory
A2: These sell at KSh 0 (bundled), yet each deducts stock. Their average cost feeds the 'Accompaniment (1 of choice)' line used inside main-dish recipes, so a main's true plate cost includes one side.
A3: Accompaniment | B3: Ingredient | C3: Qty (recipe) | D3: Qty (base) | E3: EP Unit Cost (KSh) | F3: Line Cost (KSh)
A4: Chips / Fries [ACC] | B4: Potatoes | C4: 200g | D4: 200 | E4: =VLOOKUP(B4,Ingredient_Master!$B$4:$I$79,8,FALSE()) -> 0.0875 | F4: =D4*E4 -> 17.5
B5: Cooking oil | C5: fry | D5: 20 | E5: =VLOOKUP(B5,Ingredient_Master!$B$4:$I$79,8,FALSE()) -> 0.32 | F5: =D5*E5 -> 6.4
B6: Salt | C6: season | D6: 2 | E6: =VLOOKUP(B6,Ingredient_Master!$B$4:$I$79,8,FALSE()) -> 0.03 | F6: =D6*E6 -> 0.06
A7: → Chips / Fries [ACC] cost/portion | F7: =SUM(F4:F6) -> 23.96
A8: Rice [ACC] | B8: Rice (dry) | C8: 90g dry | D8: 90 | E8: =VLOOKUP(B8,Ingredient_Master!$B$4:$I$79,8,FALSE()) -> 0.15 | F8: =D8*E8 -> 13.5
B9: Cooking oil | C9: fry | D9: 8 | E9: =VLOOKUP(B9,Ingredient_Master!$B$4:$I$79,8,FALSE()) -> 0.32 | F9: =D9*E9 -> 2.56
B10: Salt | C10: season | D10: 2 | E10: =VLOOKUP(B10,Ingredient_Master!$B$4:$I$79,8,FALSE()) -> 0.03 | F10: =D10*E10 -> 0.06
A11: → Rice [ACC] cost/portion | F11: =SUM(F8:F10) -> 16.12
A12: Ugali White [ACC] | B12: Maize flour | C12: 130g | D12: 130 | E12: =VLOOKUP(B12,Ingredient_Master!$B$4:$I$79,8,FALSE()) -> 0.07 | F12: =D12*E12 -> 9.1
B13: Salt | C13: - | D13: 1 | E13: =VLOOKUP(B13,Ingredient_Master!$B$4:$I$79,8,FALSE()) -> 0.03 | F13: =D13*E13 -> 0.03
A14: → Ugali White [ACC] cost/portion | F14: =SUM(F12:F13) -> 9.13
A15: Ugali Brown [ACC] | B15: Maize flour | C15: 150g | D15: 150 | E15: =VLOOKUP(B15,Ingredient_Master!$B$4:$I$79,8,FALSE()) -> 0.07 | F15: =D15*E15 -> 10.5
B16: Salt | C16: - | D16: 1 | E16: =VLOOKUP(B16,Ingredient_Master!$B$4:$I$79,8,FALSE()) -> 0.03 | F16: =D16*E16 -> 0.03
A17: → Ugali Brown [ACC] cost/portion | F17: =SUM(F15:F16) -> 10.53
A18: Chapati 2s [ACC] | B18: All-purpose flour | C18: 2 pc | D18: 120 | E18: =VLOOKUP(B18,Ingredient_Master!$B$4:$I$79,8,FALSE()) -> 0.13 | F18: =D18*E18 -> 15.6
B19: Cooking oil | C19: - | D19: 20 | E19: =VLOOKUP(B19,Ingredient_Master!$B$4:$I$79,8,FALSE()) -> 0.32 | F19: =D19*E19 -> 6.4
B20: Salt | C20: - | D20: 2 | E20: =VLOOKUP(B20,Ingredient_Master!$B$4:$I$79,8,FALSE()) -> 0.03 | F20: =D20*E20 -> 0.06
A21: → Chapati 2s [ACC] cost/portion | F21: =SUM(F18:F20) -> 22.06
A22: Kachumbari [ACC] | B22: Tomato | C22: - | D22: 80 | E22: =VLOOKUP(B22,Ingredient_Master!$B$4:$I$79,8,FALSE()) -> 0.13333333 | F22: =D22*E22 -> 10.666667
B23: Onion | C23: - | D23: 60 | E23: =VLOOKUP(B23,Ingredient_Master!$B$4:$I$79,8,FALSE()) -> 0.13333333 | F23: =D23*E23 -> 8
B24: Coriander (dhania) | C24: - | D24: 5 | E24: =VLOOKUP(B24,Ingredient_Master!$B$4:$I$79,8,FALSE()) -> 0.11111111 | F24: =D24*E24 -> 0.55555556
B25: Lemon | C25: - | D25: 0.3 | E25: =VLOOKUP(B25,Ingredient_Master!$B$4:$I$79,8,FALSE()) -> 15 | F25: =D25*E25 -> 4.5
A26: → Kachumbari [ACC] cost/portion | F26: =SUM(F22:F25) -> 23.722222
A28: AVERAGE accompaniment cost (drives 'Accompaniment (1 of choice)' on Ingredient_Master) | F28: =(F7+F11+F14+F17+F21+F26)/6 -> 17.587037

Sheet Modifiers_and_Variants
A1: MODIFIERS & VARIANTS — how size & add-on pricing flows to BOM, stock and final price
A3: A. PIZZA SIZE VARIANTS — same recipe scaled by surface area; each size is its own sellable SKU that deducts its own BOM
A4: Size | B4: Diameter | C4: Area factor (vs L) | D4: Margherita price | E4: Margherita BOM cost | F4: FC % | G4: Hawaiian price | H4: Hawaiian BOM cost | I4: FC %
A5: Small (S) | B5: 9" | C5: 0.5625 | D5: 700 | E5: =C5*SUMIF(Recipe_BOM!$A$4:$A$288,"PIZ003",Recipe_BOM!$H$4:$H$288) -> 215.865 | F5: =E5/D5 -> 0.30837857 | G5: 800 | H5: =C5*SUMIF(Recipe_BOM!$A$4:$A$288,"PIZ012",Recipe_BOM!$H$4:$H$288) -> 263.7636 | I5: =H5/G5 -> 0.3297045
A6: Medium (M) | B6: 10.5" | C6: 0.7639 | D6: 1000 | E6: =C6*SUMIF(Recipe_BOM!$A$4:$A$288,"PIZ003",Recipe_BOM!$H$4:$H$288) -> 293.15426 | F6: =E6/D6 -> 0.29315426 | G6: 1300 | H6: =C6*SUMIF(Recipe_BOM!$A$4:$A$288,"PIZ012",Recipe_BOM!$H$4:$H$288) -> 358.20269 | I6: =H6/G6 -> 0.27554053
A7: Large (L) | B7: 12" | C7: 1 | D7: 1200 | E7: =C7*SUMIF(Recipe_BOM!$A$4:$A$288,"PIZ003",Recipe_BOM!$H$4:$H$288) -> 383.76 | F7: =E7/D7 -> 0.3198 | G7: 1600 | H7: =C7*SUMIF(Recipe_BOM!$A$4:$A$288,"PIZ012",Recipe_BOM!$H$4:$H$288) -> 468.91306 | I7: =H7/G7 -> 0.29307066
A8: Logic: choosing a size = selecting a variant SKU. The POS multiplies the master (Large) recipe quantities by the area factor, so a Small pizza deducts ~56% of each topping's grams from stock and a Medium ~76%. Price is set per size; cost scales with the BOM.
A10: B. TOPPING / ADD-ON MODIFIERS — modifier carries its own mini-BOM; upcharge is set so modifier FC% stays on target
A11: Modifier | B11: Applies to | C11: Ingredient | D11: Qty (base) | E11: Unit | F11: EP Unit Cost | G11: Modifier Cost | H11: Upcharge price | I11: Modifier FC %
A12: Extra Cheese | B12: Burger/Pizza/Sandwich | C12: Cheese slice (cheddar) | D12: 40 | E12: g | F12: =VLOOKUP(C12,Ingredient_Master!$B$4:$I$79,8,FALSE()) -> 1 | G12: =D12*F12 -> 40 | H12: 200 | I12: =G12/H12 -> 0.2
A13: Add Bacon | B13: Burger | C13: Bacon rashers | D13: 40 | E13: g | F13: =VLOOKUP(C13,Ingredient_Master!$B$4:$I$79,8,FALSE()) -> 1.1111111 | G13: =D13*F13 -> 44.444444 | H13: 250 | I13: =G13/H13 -> 0.17777778
A14: Extra Mozzarella | B14: Pizza | C14: Mozzarella cheese | D14: 50 | E14: g | F14: =VLOOKUP(C14,Ingredient_Master!$B$4:$I$79,8,FALSE()) -> 1.1 | G14: =D14*F14 -> 55 | H14: 200 | I14: =G14/H14 -> 0.275
A15: Extra Pepperoni | B15: Pizza | C15: Pepperoni | D15: 40 | E15: g | F15: =VLOOKUP(C15,Ingredient_Master!$B$4:$I$79,8,FALSE()) -> 1.2244898 | G15: =D15*F15 -> 48.979592 | H15: 250 | I15: =G15/H15 -> 0.19591837
A16: Extra Flavoured Syrup | B16: Coffee/Shake | C16: Flavoured syrup | D16: 20 | E16: ml | F16: =VLOOKUP(C16,Ingredient_Master!$B$4:$I$79,8,FALSE()) -> 0.8 | G16: =D16*F16 -> 16 | H16: 200 | I16: =G16/H16 -> 0.08
A17: Extra Honey | B17: Tea/Coffee | C17: Honey (own) | D17: 20 | E17: g | F17: =VLOOKUP(C17,Ingredient_Master!$B$4:$I$79,8,FALSE()) -> 0.55 | G17: =D17*F17 -> 11 | H17: 60 | I17: =G17/H17 -> 0.18333333
A18: Extra Shot (single→double) | B18: Coffee | C18: Coffee beans (ground) | D18: 8 | E18: g | F18: =VLOOKUP(C18,Ingredient_Master!$B$4:$I$79,8,FALSE()) -> 2.5 | G18: =D18*F18 -> 20 | H18: 100 | I18: =G18/H18 -> 0.2
A19: Plate Inscription | B19: Cakes/plates | C19: Chocolate sauce/ganache | D19: 15 | E19: g | F19: =VLOOKUP(C19,Ingredient_Master!$B$4:$I$79,8,FALSE()) -> 0.9 | G19: =D19*F19 -> 13.5 | H19: 150 | I19: =G19/H19 -> 0.09
A20: Takeaway Packaging | B20: Any | C20: Pizza box | D20: 1 | E20: pc | F20: =VLOOKUP(C20,Ingredient_Master!$B$4:$I$79,8,FALSE()) -> 80 | G20: =D20*F20 -> 80 | H20: 80 | I20: =G20/H20 -> 1
A21: Logic: a modifier = a small recipe attached to a parent item. When selected it (1) adds its mini-BOM to the order so the extra grams are deducted from stock, and (2) adds its upcharge to the line price. The upcharge is set above modifier cost to keep a healthy margin (modifier FC% column). Negative modifiers (e.g. 'no cheese') simply omit the BOM line and can carry a negative price.
A23: C. CHEESE-BURGER WORKED EXAMPLE — base patty (BUR001) + 'Extra Cheese' modifier = priced cheese burger (BUR006)
A24: Beef Burger base cost/serving (BUR001) | D24: =Recipe_Costing!G25 -> 196.11042
A25: + Extra Cheese modifier cost | D25: =G12 -> 40
A26: Beef Cheese Burger plate cost (base + cheese) | D26: =D24+D25 -> 236.11042
A27: Beef Cheese Burger price (BUR006) | D27: 1050
A28: Resulting Food Cost % | D28: =D26/D27 -> 0.22486707

Sheet NonRecipe_Goods
A1: NO-RECIPE GOODS — resale / packaged / portioned items (cost is purchase price, not a recipe)
A2: These items need NO recipe in the POS — only a purchase cost and a sell price. Spirits/wine-by-tot are 'portioned goods': the bottle is the stock unit and each tot/glass deducts a fraction. Purchase costs are typical Kenyan trade estimates — adjust to your invoices.
A3: Code | B3: Item | C3: Sell Price (KSh) | D3: Purchase/Pour Cost (KSh) | E3: Gross Profit (KSh) | F3: Margin %
A4: SOD001 | B4: Soda 300ml | C4: 150 | D4: 35 | E4: =C4-D4 -> 115 | F4: =(C4-D4)/C4 -> 0.76666667
A5: SOD002 | B5: Plastic Soda 500ml | C5: 150 | D5: 45 | E5: =C5-D5 -> 105 | F5: =(C5-D5)/C5 -> 0.7
A6: SPA001 | B6: Sparkling Water 750ml | C6: 300 | D6: 120 | E6: =C6-D6 -> 180 | F6: =(C6-D6)/C6 -> 0.6
A7: SPA002 | B7: Sparkling Water 500ml | C7: 190 | D7: 80 | E7: =C7-D7 -> 110 | F7: =(C7-D7)/C7 -> 0.57894737
A8: WAT001 | B8: Urban Mist 500ml | C8: 160 | D8: 25 | E8: =C8-D8 -> 135 | F8: =(C8-D8)/C8 -> 0.84375
A9: WAT002 | B9: Urban Mist 1Ltr | C9: 320 | D9: 45 | E9: =C9-D9 -> 275 | F9: =(C9-D9)/C9 -> 0.859375
A10: 4TH001 | B10: 4th Street Red Dry 750ml | C10: 2500 | D10: 1200 | E10: =C10-D10 -> 1300 | F10: =(C10-D10)/C10 -> 0.52
A11: 4TH002 | B11: 4th Street Dry White 750ml | C11: 2500 | D11: 1200 | E11: =C11-D11 -> 1300 | F11: =(C11-D11)/C11 -> 0.52
A12: FOUR001 | B12: Four Cousins Sweet Red 750ml | C12: 3000 | D12: 1500 | E12: =C12-D12 -> 1500 | F12: =(C12-D12)/C12 -> 0.5
A13: DRST001 | B13: Drosthof Dry White 750ml | C13: 2850 | D13: 1500 | E13: =C13-D13 -> 1350 | F13: =(C13-D13)/C13 -> 0.47368421
A14: BLU002 | B14: Blue Curacao 750ml | C14: 5000 | D14: 2700 | E14: =C14-D14 -> 2300 | F14: =(C14-D14)/C14 -> 0.46
A15: HNY001 | B15: Urban Loft Honey 1kg | C15: 1100 | D15: 550 | E15: =C15-D15 -> 550 | F15: =(C15-D15)/C15 -> 0.5
... A25: TEQ001 | B25: Tequila Tot | C25: 350 | D25: 140 | E25: =C25-D25 -> 210 | F25: =(C25-D25)/C25 -> 0.6
